sdmx2jsonld/README.md
sdmx2jsonld/__init__.py
sdmx2jsonld/common/__init__.py
sdmx2jsonld/common/classprecedence.py
sdmx2jsonld/common/commonclass.py
sdmx2jsonld/common/config.py
sdmx2jsonld/common/datatypeconversion.py
sdmx2jsonld/common/listmanagement.py
sdmx2jsonld/common/rdf.py
sdmx2jsonld/common/regparser.py
sdmx2jsonld/common/tzinfos.py
sdmx2jsonld/cube/__init__.py
sdmx2jsonld/cube/measuretype.py
sdmx2jsonld/exceptions/__init__.py
sdmx2jsonld/exceptions/exceptions.py
sdmx2jsonld/grammar/grammar.lark
sdmx2jsonld/sdmxattributes/__init__.py
sdmx2jsonld/sdmxattributes/code.py
sdmx2jsonld/sdmxattributes/compilingorg.py
sdmx2jsonld/sdmxattributes/confirmationStatus.py
sdmx2jsonld/sdmxattributes/currency.py
sdmx2jsonld/sdmxattributes/dataComp.py
sdmx2jsonld/sdmxattributes/decimals.py
sdmx2jsonld/sdmxattributes/dissorg.py
sdmx2jsonld/sdmxattributes/observationStatus.py
sdmx2jsonld/sdmxattributes/sdmxattribute.py
sdmx2jsonld/sdmxattributes/timeFormat.py
sdmx2jsonld/sdmxattributes/timePerCollect.py
sdmx2jsonld/sdmxattributes/title.py
sdmx2jsonld/sdmxattributes/unitmult.py
sdmx2jsonld/sdmxconcepts/__init__.py
sdmx2jsonld/sdmxconcepts/cogconceptschema.py
sdmx2jsonld/sdmxconcepts/compilingorgconcept.py
sdmx2jsonld/sdmxconcepts/confstatusconcept.py
sdmx2jsonld/sdmxconcepts/currencyconcept.py
sdmx2jsonld/sdmxconcepts/datacompconcept.py
sdmx2jsonld/sdmxconcepts/decimals.py
sdmx2jsonld/sdmxconcepts/dissorgconcept.py
sdmx2jsonld/sdmxconcepts/freqconcept.py
sdmx2jsonld/sdmxconcepts/obsstatusconcept.py
sdmx2jsonld/sdmxconcepts/refareaconcept.py
sdmx2jsonld/sdmxconcepts/sdmxconcept.py
sdmx2jsonld/sdmxconcepts/timePerCollectConcept.py
sdmx2jsonld/sdmxconcepts/timeformatconcept.py
sdmx2jsonld/sdmxconcepts/timeperiodconcept.py
sdmx2jsonld/sdmxconcepts/titleConcept.py
sdmx2jsonld/sdmxconcepts/unitmultconcept.py
sdmx2jsonld/sdmxdimensions/__init__.py
sdmx2jsonld/sdmxdimensions/frequency.py
sdmx2jsonld/sdmxdimensions/refarea.py
sdmx2jsonld/sdmxdimensions/sdmxdimension.py
sdmx2json_ld-1.0.0.dist-info/LICENSE
sdmx2json_ld-1.0.0.dist-info/METADATA
sdmx2json_ld-1.0.0.dist-info/WHEEL
sdmx2json_ld-1.0.0.dist-info/RECORD
