Metadata-Version: 2.1
Name: sdmx2json-ld
Version: 1.0.0
Summary: A SDMX in RDF Turtle 1.1 format parser to generate valid JSON-LD and send to FIWARE Context Brokers using ETSI NGSI-LD.
Home-page: https://github.com/flopezag/IoTAgent-Turtle
Keywords: parsing,ETSI NGSI-LD,SDMX
Author: Fernando López
Author-email: fernando.lopez@fiware.org
Requires-Python: >=3.8,<4.0
Classifier: Programming Language :: Python :: 3
Classifier: Programming Language :: Python :: 3.8
Classifier: Programming Language :: Python :: 3.9
Classifier: Programming Language :: Python :: 3.10
Classifier: Programming Language :: Python :: 3.11
Classifier: Topic :: Software Development :: Build Tools
Classifier: Topic :: Software Development :: Libraries :: Python Modules
Requires-Dist: docopt (==0.6.2)
Requires-Dist: fastapi (==0.100.0)
Requires-Dist: hi-dateinfer (==0.4.6)
Requires-Dist: lark (==1.1.7)
Requires-Dist: loguru (==0.7.0)
Requires-Dist: python-dateutil (==2.8.2)
Requires-Dist: python-multipart (==0.0.6)
Requires-Dist: rdflib (==6.3.2)
Requires-Dist: requests (==2.31.0)
Requires-Dist: schema (==0.7.5)
Requires-Dist: secure (==0.3.0)
Requires-Dist: uvicorn (==0.23.1)
Project-URL: Repository, https://github.com/flopezag/IoTAgent-Turtle
